nvidia/__init__.py
nvidia/nvtx/__init__.py
nvidia/nvtx/include/__init__.py
nvidia/nvtx/include/nvtx3/nvToolsExt.h
nvidia/nvtx/include/nvtx3/nvToolsExtCuda.h
nvidia/nvtx/include/nvtx3/nvToolsExtCudaRt.h
nvidia/nvtx/include/nvtx3/nvToolsExtOpenCL.h
nvidia/nvtx/include/nvtx3/nvToolsExtSync.h
nvidia/nvtx/include/nvtx3/nvtx3.hpp
nvidia/nvtx/include/nvtx3/nvtxDetail/nvtxImpl.h
nvidia/nvtx/include/nvtx3/nvtxDetail/nvtxImplCore.h
nvidia/nvtx/include/nvtx3/nvtxDetail/nvtxImplCudaRt_v3.h
nvidia/nvtx/include/nvtx3/nvtxDetail/nvtxImplCuda_v3.h
nvidia/nvtx/include/nvtx3/nvtxDetail/nvtxImplOpenCL_v3.h
nvidia/nvtx/include/nvtx3/nvtxDetail/nvtxImplSync_v3.h
nvidia/nvtx/include/nvtx3/nvtxDetail/nvtxInit.h
nvidia/nvtx/include/nvtx3/nvtxDetail/nvtxInitDecls.h
nvidia/nvtx/include/nvtx3/nvtxDetail/nvtxInitDefs.h
nvidia/nvtx/include/nvtx3/nvtxDetail/nvtxLinkOnce.h
nvidia/nvtx/include/nvtx3/nvtxDetail/nvtxTypes.h
nvidia/nvtx/lib/__init__.py
nvidia/nvtx/lib/libnvtx3interop.so.1
nvidia_nvtx_cu12-12.9.19.dist-info/License.txt
nvidia_nvtx_cu12-12.9.19.dist-info/METADATA
nvidia_nvtx_cu12-12.9.19.dist-info/WHEEL
nvidia_nvtx_cu12-12.9.19.dist-info/top_level.txt
nvidia_nvtx_cu12-12.9.19.dist-info/RECORD
